{"current":{"typeahead_collection":"all","typekit":"gor6epv","main_blog":"news","sidebar_linklist_1":"collections","sidebar_linklist_2":"","sidebar_linklist_3":"","welcome_message":"welcome","frontpage_collection":"frontpage","frontpage_collection_title":"Feature Products","slideshow_speed":"5000","show_image_1":true,"image_1_link":"","image_1_desc":"","show_image_2":true,"image_2_link":"","image_2_desc":"","show_image_3":true,"image_3_link":"","image_3_desc":"","show_image_4":true,"image_4_link":"","image_4_desc":"","show_image_5":false,"image_5_link":"","image_5_desc":"","show_credits":true,"shop_tagline":"","customer_layout":"theme"}}